[{"opt21133":"\u00danica","quantity":"1","idicart":"21133-92","idproducto":"14529","iddetalle":"21133","nombre_producto":"Zarcillos de Bolitas","descripcion_producto":"Zarcillos Lisos con Cadena Coreana con Bolitas en los Extremos . Aretes , Pendientes , Cierre Anzuelo .","img_producto":"admin\/catalog\/IMG_20210210_103023829afcc11115f19d47bbf4caf5c7b5c5.jpg","seltalla":"\u00danica","idseltalla":"92","unit_price":"3.99","subtotal":3.9900000000000002131628207280300557613372802734375},{"opt4950":"55","quantity":2,"idicart":"4950-15","idproducto":"3920","iddetalle":"4950","nombre_producto":"A3P1206LPC","descripcion_producto":"Cadena Figaro 120 con Pave . Cadena 3 y 1 , Cadena Cartier .","img_producto":"admin\/catalog\/IMG_20190729_145553_compress126dc9e783ec84180310f1da9ed1b357b9.jpg","seltalla":"55","idseltalla":"15","unit_price":"21.58","subtotal":21.5799999999999982946974341757595539093017578125}]