[{"opt15127":"\u00danica","quantity":"1","idicart":"15127-92","idproducto":"10829","iddetalle":"15127","nombre_producto":"Argollas Bali 1.5*14mm","descripcion_producto":"(058) Argollas , Aretes , Candongas , Chapas , Aros , Cierre Cl\u00e1sico o Aguja .","img_producto":"admin\/catalog\/IMG_20201012_113329c7a2b8e4dad776ed1c47bb0a585ae25d.jpg","seltalla":"\u00danica","idseltalla":"92","unit_price":"2.10","subtotal":2.100000000000000088817841970012523233890533447265625},{"opt15118":"\u00danica","quantity":"1","idicart":"15118-92","idproducto":"10820","iddetalle":"15118","nombre_producto":"Argollas Bali 1.5*14mm","descripcion_producto":"(058) Argollas , Aretes , Candongas , Chapas , Aros , Cierre Cl\u00e1sico o Aguja .","img_producto":"admin\/catalog\/IMG_20201012_112254d63de49900b80afa7a4fe1d5e3f789cd.jpg","seltalla":"\u00danica","idseltalla":"92","unit_price":"2.24","subtotal":2.2400000000000002131628207280300557613372802734375},{"opt15123":"\u00danica","quantity":"1","idicart":"15123-92","idproducto":"10822","iddetalle":"15123","nombre_producto":"Argollas Bali 1.5*17mm","descripcion_producto":"(058) Argollas , Aretes , Candongas , Chapas , Aros , Cierre Cl\u00e1sico o Aguja .","img_producto":"admin\/catalog\/IMG_20201012_113449ee27409c04cac63a22ad14399986c0c5.jpg","seltalla":"\u00danica","idseltalla":"92","unit_price":"2.94","subtotal":2.939999999999999946709294817992486059665679931640625},{"opt15126":"\u00danica","quantity":"1","idicart":"15126-92","idproducto":"10828","iddetalle":"15126","nombre_producto":"Argollas Bali 1.5*16mm","descripcion_producto":"(058) Argollas , Aretes , Candongas , Chapas , Aros , Cierre Cl\u00e1sico o Aguja .","img_producto":"admin\/catalog\/IMG_20201012_1124374f2848af810001e5df2d8c1ec3bd298c.jpg","seltalla":"\u00danica","idseltalla":"92","unit_price":"2.24","subtotal":2.2400000000000002131628207280300557613372802734375},{"opt15074":"\u00danica","quantity":"1","idicart":"15074-92","idproducto":"10784","iddetalle":"15074","nombre_producto":"Argollas 2.0*14mm","descripcion_producto":"(089) Argollas , Aretes , Candongas ,Chapas , Aros , Cierre Cl\u00e1sico o Aguja .","img_producto":"admin\/catalog\/IMG_20201012_095819315f6ecf3fe00c9189dfde90272f558c.jpg","seltalla":"\u00danica","idseltalla":"92","unit_price":"1.60","subtotal":1.600000000000000088817841970012523233890533447265625},{"opt14793":"\u00danica","quantity":"1","idicart":"14793-92","idproducto":"10629","iddetalle":"14793","nombre_producto":"Zarcillos Largos de Estrellas","descripcion_producto":"(039) Zarcillos Largos de Circones de Estrellas . Aretes , Pendientes , Puntos de Luz , Cierre Topito  . (BRY-ZD191049IS)","img_producto":"admin\/catalog\/BRY_ZD191049ISeecae39cab88871c4e6ca682807eadde.jpg","seltalla":"\u00danica","idseltalla":"92","unit_price":"4.75","subtotal":4.75},{"opt14531":"\u00danica","quantity":"1","idicart":"14531-92","idproducto":"8165","iddetalle":"14531","nombre_producto":"Zarcillo de Coraz\u00f3n 6mm","descripcion_producto":"(051) Zarcillos de Coraz\u00f3n , Zarcillos , Aretes , Pendientes , Coraz\u00f3n . Cierre Topito ","img_producto":"admin\/catalog\/IMG_20201001_1315100a83c6111bdc1ae946aa5889c79e8456.jpg","seltalla":"\u00danica","idseltalla":"92","unit_price":"1.45","subtotal":1.4499999999999999555910790149937383830547332763671875},{"opt14128":"\u00danica","quantity":"1","idicart":"14128-92","idproducto":"10232","iddetalle":"14128","nombre_producto":"Argollas 12mm","descripcion_producto":"(052) Argollas , Candongas , Chapas , Aros , Cierre Italiano . (CB12-1)","img_producto":"admin\/catalog\/IMG_20200925_152542883a620a5b319562681d8c4a6f8a05a1.jpg","seltalla":"\u00danica","idseltalla":"92","unit_price":"1.80","subtotal":1.8000000000000000444089209850062616169452667236328125},{"opt13711":"\u00danica","quantity":"1","idicart":"13711-92","idproducto":"10020","iddetalle":"13711","nombre_producto":"Argollas de Estrella 15mm","descripcion_producto":"(001) Argollas , Candongas , Chapas , Aros , Estrella . Cierre Cl\u00e1sico o de Aguja .","img_producto":"admin\/catalog\/IMG_20200918_1419439b1a43b79439bca2a2858e1f4a9816ce.jpg","seltalla":"\u00danica","idseltalla":"92","unit_price":"2.60","subtotal":2.600000000000000088817841970012523233890533447265625},{"opt13707":"\u00danica","quantity":"1","idicart":"13707-92","idproducto":"10014","iddetalle":"13707","nombre_producto":"Argollas 15mm","descripcion_producto":"(001) Argollas , Candongas , Chapas , Aros , Cierre Cl\u00e1sico  o de Aguja .","img_producto":"admin\/catalog\/IMG_20200918_130524b763cb958206303e9ab0e2632b6c1e4e.jpg","seltalla":"\u00danica","idseltalla":"92","unit_price":"1.69","subtotal":1.689999999999999946709294817992486059665679931640625},{"opt13617":"\u00danica","quantity":"1","idicart":"13617-92","idproducto":"8715","iddetalle":"13617","nombre_producto":"Argollas Corazones de N\u00e1car 1.5*14mm","descripcion_producto":"(022) Argollas , Aretes , Candongas , Chapas , Aros , Corazones , N\u00e1car , Cierre Cl\u00e1sico o de Aguja  . (1.5*14mm)","img_producto":"admin\/catalog\/IMG_20200917_111608d405e5c95315943068a1cfafa06ad659.jpg","seltalla":"\u00danica","idseltalla":"92","unit_price":"2.90","subtotal":2.899999999999999911182158029987476766109466552734375},{"opt16251":"\u00danica","quantity":"1","idicart":"16251-92","idproducto":"11328","iddetalle":"16251","nombre_producto":"Huggies Huella de Perro ","descripcion_producto":"(039) Huggies Esmaltado de Huella de Perro FDI . Aretes , Zarcillos , Mascotas , Animales , Perrito , Cierre Huggies .(CJ048756)","img_producto":"admin\/catalog\/CJ048756 _4_791d71f5ff19acde97b99feb8b8a78f0.jpg","seltalla":"\u00danica","idseltalla":"92","unit_price":"3.52","subtotal":3.520000000000000017763568394002504646778106689453125},{"opt16249":"\u00danica","quantity":"1","idicart":"16249-92","idproducto":"11328","iddetalle":"16249","nombre_producto":"Huggies Huella de Perro ","descripcion_producto":"(039) Huggies Esmaltado de Huella de Perro FDI . Aretes , Zarcillos , Mascotas , Animales , Perrito , Cierre Huggies .(CJ048756)","img_producto":"admin\/catalog\/CJ048756 _3_8243e67a9a58fa75655d171628b81340.jpg","seltalla":"\u00danica","idseltalla":"92","unit_price":"3.52","subtotal":3.520000000000000017763568394002504646778106689453125},{"opt15680":"\u00danica","quantity":"1","idicart":"15680-92","idproducto":"9752","iddetalle":"15680","nombre_producto":"Zarcillos de Luna","descripcion_producto":"(091) Zarcillos de Luna . Zarcillos , Aretes , Pendientes , Luna , Moon , Cierre Topito . (E8921)","img_producto":"admin\/catalog\/IMG_20201021_142444bad28acf5199b190282e65486e453f27.jpg","seltalla":"\u00danica","idseltalla":"92","unit_price":"3.36","subtotal":3.359999999999999875655021241982467472553253173828125},{"opt12008":"\u00danica","quantity":"1","idicart":"12008-92","idproducto":"7961","iddetalle":"12008","nombre_producto":"Trepadores de C\u00edrculos ","descripcion_producto":"(074) Zarcillos Trepadores de C\u00edrculos . Zarcillos , Aretes , Pendientes , Trepadores . (EA1095)","img_producto":"admin\/catalog\/IMG_20200827_150408e1fea3461791d1e46fe2a26273ed9e3f.jpg","seltalla":"\u00danica","idseltalla":"92","unit_price":"7.14","subtotal":7.13999999999999968025576890795491635799407958984375},{"opt12004":"\u00danica","quantity":"1","idicart":"12004-92","idproducto":"5442","iddetalle":"12004","nombre_producto":"Trepadores","descripcion_producto":"(074) Zarcillos Trepadores . \r\nZarcillos , Aretes , Pendientes , Trepadores .","img_producto":"admin\/catalog\/IMG_20200827_151031acc6153a0e068faf14d0b3c27b333405.jpg","seltalla":"\u00danica","idseltalla":"92","unit_price":"5.61","subtotal":5.61000000000000031974423109204508364200592041015625},{"opt11561":"\u00danica","quantity":"1","idicart":"11561-92","idproducto":"8892","iddetalle":"11561","nombre_producto":"Argollas de Delfines","descripcion_producto":"(096) Argollas , Aretes , Candongas ,Chapas , Aros , Cierre Italiano . (AS-064)","img_producto":"admin\/catalog\/_cp7W7Hg _2_dbb86f19849e401861b60278d27ab43b.jpg","seltalla":"\u00danica","idseltalla":"92","unit_price":"1.95","subtotal":1.9499999999999999555910790149937383830547332763671875},{"opt11151":"\u00danica","quantity":"1","idicart":"11151-92","idproducto":"8641","iddetalle":"11151","nombre_producto":"Argollas con Bolitas 1.5*14mm","descripcion_producto":"(058) Zarcillos , Aretes , Pendientes , Argollas , Candongas , Bolita , Cierre Cl\u00e1sico o de Aguja . (1.5*14mm)","img_producto":"admin\/catalog\/IMG_20200813_092805891e23ef408379cda59087a0d3175bce.jpg","seltalla":"\u00danica","idseltalla":"92","unit_price":"1.54","subtotal":1.54000000000000003552713678800500929355621337890625}]